{
  "viewBox": "0 0 16 16",
  "children": [
    {
      "tag": "path",
      "d": "M4,2.75 C4.33500067,2.75 6.83500067,2.75 11.5,2.75 L13.25,4.5 C13.25,9.16666667 13.25,11.6666667 13.25,12 C13.25,12.66 12.66,13.25 12,13.25 C11.5,13.25 4.5,13.25 4,13.25 C3.35311981,13.25 2.75,12.66 2.75,12 C2.75,11.5 2.75,4.5 2.75,4 C2.75,3.33 3.33,2.75 4,2.75 Z",
      "id": "Path",
      "stroke-opacity": "0.5",
      "stroke": "currentColor",
      "stroke-width": "1.5",
      "stroke-linejoin": "round",
      "fill": "none"
    },
    {
      "tag": "rect",
      "id": "Rectangle",
      "fill": "currentColor",
      "fill-rule": "evenodd",
      "x": "5",
      "y": "8",
      "width": "6",
      "height": "4",
      "rx": "1"
    },
    {
      "tag": "path",
      "d": "M9,2 C9.55228475,2 10,2.44771525 10,3 L10,6 C10,6.55228475 9.55228475,7 9,7 L6,7 C5.44771525,7 5,6.55228475 5,6 L5,3 C5,2.44771525 5.44771525,2 6,2 L9,2 Z M7.5,3.5 L6.25,3.5 L6.25,5.5 L7.5,5.5 L7.5,3.5 Z",
      "id": "Rectangle-Copy",
      "fill": "currentColor",
      "fill-rule": "nonzero"
    }
  ]
}
